owlib/__init__.py
owlib/client.py
owlib/exceptions.py
owlib/knowledge_base.py
owlib/models.py
owlib/py.typed
owlib/utils.py
owlib-0.1.0.dist-info/licenses/LICENSE
owlib-0.1.0.dist-info/METADATA
owlib-0.1.0.dist-info/WHEEL
owlib-0.1.0.dist-info/top_level.txt
owlib-0.1.0.dist-info/RECORD
