Metadata-Version: 2.4
Name: owlib
Version: 0.1.0
Summary: Python SDK for the Owlib AI Knowledge Platform
Author-email: Xiang Fei <xfey99@gmail.com>
Maintainer-email: Xiang Fei <xfey99@gmail.com>
License: MIT License
Project-URL: Homepage, https://owlib.ai
Project-URL: Documentation, https://docs.owlib.ai
Project-URL: Repository, https://github.com/owlib/owlib-python
Project-URL: Bug Tracker, https://github.com/owlib/owlib-python/issues
Project-URL: Changelog, https://github.com/owlib/owlib-python/blob/main/CHANGELOG.md
Keywords: ai,artificial-intelligence,knowledge-base,embedding,vector-search,nlp
Classifier: Development Status :: 4 - Beta
Classifier: Intended Audience :: Developers
Classifier: Topic :: Software Development :: Libraries :: Python Modules
Classifier: Topic :: Scientific/Engineering :: Artificial Intelligence
Classifier: License :: OSI Approved :: MIT License
Classifier: Programming Language :: Python :: 3
Classifier: Programming Language :: Python :: 3.7
Classifier: Programming Language :: Python :: 3.8
Classifier: Programming Language :: Python :: 3.9
Classifier: Programming Language :: Python :: 3.10
Classifier: Programming Language :: Python :: 3.11
Classifier: Programming Language :: Python :: 3.12
Classifier: Operating System :: OS Independent
Requires-Python: >=3.7
License-File: LICENSE
Requires-Dist: requests>=2.28.0
Requires-Dist: python-dotenv>=0.19.0
Provides-Extra: dev
Requires-Dist: pytest>=6.0.0; extra == "dev"
Requires-Dist: pytest-cov>=2.0.0; extra == "dev"
Requires-Dist: black>=22.0.0; extra == "dev"
Requires-Dist: flake8>=4.0.0; extra == "dev"
Requires-Dist: mypy>=0.900; extra == "dev"
Requires-Dist: twine>=3.0.0; extra == "dev"
Requires-Dist: build>=0.7.0; extra == "dev"
Provides-Extra: test
Requires-Dist: pytest>=6.0.0; extra == "test"
Requires-Dist: pytest-cov>=2.0.0; extra == "test"
Requires-Dist: pytest-mock>=3.0.0; extra == "test"
Requires-Dist: responses>=0.20.0; extra == "test"
Dynamic: license-file
